<?xml version="1.0" encoding="UTF-8"?>
<window type="dialog" id="1195">
    <visible>Skin.HasSetting(home.netflix.autoplay.trailer) + $EXP[TrailerIsReady] + [
    [String.IsEqual(Skin.String(Value_Items_Flix_Trailer_Delay),3) + System.IdleTime(3)]
    |
    [[String.IsEqual(Skin.String(Value_Items_Flix_Trailer_Delay),5) | !Skin.String(Value_Items_Flix_Trailer_Delay)] + System.IdleTime(5)]
    |
    [String.IsEqual(Skin.String(Value_Items_Flix_Trailer_Delay),7) + System.IdleTime(7)]
    |
    [String.IsEqual(Skin.String(Value_Items_Flix_Trailer_Delay),9) + System.IdleTime(9)]
    |
    [String.IsEqual(Skin.String(Value_Items_Flix_Trailer_Delay),11) + System.IdleTime(11)]
    |
    [String.IsEqual(Skin.String(Value_Items_Flix_Trailer_Delay),13) + System.IdleTime(13)]
    |
    [String.IsEqual(Skin.String(Value_Items_Flix_Trailer_Delay),15) + System.IdleTime(15)]
    ] + !System.IdleTime(30)</visible>

    <!-- START BACKGROUND FADE -->

    <onload>SetProperty(TrailerFade,1,Home)</onload>

    <!-- SET TRAILER PATH -->

    <onload>SetProperty(TrailerPath,$INFO[ListItem.Trailer],Home)</onload>
    <onload>SetProperty(TrailerPath2,$INFO[ListItem.Trailer],Home)</onload>

    <!-- START TRAILER -->

    <onload>PlayMedia($ESCINFO[ListItem.Trailer],1)</onload>
    <controls />
</window>
